wasp_launcher
